couchdb3/__init__.py
couchdb3/base.py
couchdb3/database.py
couchdb3/document.py
couchdb3/exceptions.py
couchdb3/server.py
couchdb3/utils.py
couchdb3/view.py
couchdb3-2.0.2.dist-info/LICENSE
couchdb3-2.0.2.dist-info/METADATA
couchdb3-2.0.2.dist-info/WHEEL
couchdb3-2.0.2.dist-info/RECORD
