Metadata-Version: 2.3
Name: couchdb3
Version: 2.0.2
Summary: A wrapper around the CouchDB API.
License: MIT
Author: Nikolai Vlahovic
Author-email: vlahovic.nikolai@gmail.com
Requires-Python: >= 3.10
Classifier: License :: OSI Approved :: MIT License
Classifier: Programming Language :: Python :: 3
Classifier: Programming Language :: Python :: 3.10
Classifier: Programming Language :: Python :: 3.11
Classifier: Programming Language :: Python :: 3.12
Classifier: Programming Language :: Python :: 3.13
Requires-Dist: requests (>=2.32.4,<3.0.0)
Project-URL: Documentation, https://n-vlahovic.github.io/couchdb3/
Project-URL: Homepage, https://github.com/N-Vlahovic/couchdb3
Project-URL: Issues, https://github.com/N-Vlahovic/couchdb3/issues
Project-URL: Repository, https://github.com/N-Vlahovic/couchdb3.git
